expecttest/__init__.py
expecttest/py.typed
expecttest-0.2.0.dist-info/LICENSE
expecttest-0.2.0.dist-info/METADATA
expecttest-0.2.0.dist-info/WHEEL
expecttest-0.2.0.dist-info/RECORD
