Metadata-Version: 2.1
Name: expecttest
Version: 0.2.0
Summary: 
Home-page: https://github.com/ezyang/expecttest
License: MIT
Author: Edward Z. Yang
Author-email: ezyang@mit.edu
Requires-Python: >=3.8,<4.0
Classifier: License :: OSI Approved :: MIT License
Classifier: Operating System :: OS Independent
Classifier: Programming Language :: Python :: 3
Classifier: Programming Language :: Python :: 3.8
Classifier: Programming Language :: Python :: 3.9
Classifier: Programming Language :: Python :: 3.10
Classifier: Programming Language :: Python :: 3.11
Classifier: Programming Language :: Python :: 3.12
Project-URL: Repository, https://github.com/ezyang/expecttest
